setup.py
clinical_trials/__init__.py
clinical_trials/clinical_trials.py
clinical_trials.egg-info/PKG-INFO
clinical_trials.egg-info/SOURCES.txt
clinical_trials.egg-info/dependency_links.txt
clinical_trials.egg-info/top_level.txt
clinical_trials/api/__init__.py
clinical_trials/api/api.py
clinical_trials/api/test_api.py
clinical_trials/api/xml2dict/__init__.py
clinical_trials/api/xml2dict/object_dict.py
clinical_trials/api/xml2dict/test_xml2dict.py
clinical_trials/api/xml2dict/xml2dict.py