Metadata-Version: 1.0
Name: clinical-trials
Version: 1.1
Summary: Python wrapper for the Clincal Trials API.
Home-page: https://github.com/codeforamerica/Clinical-Trials-Python
Author: Zach Williams
Author-email: zach@codeforamerica.org
License: BSD
Keywords: clinical trials,clinicaltrials,clinical_trials
Platform: UNKNOWN
Classifier: Development Status :: 5 - Production/Stable
Classifier: Intended Audience :: Developers
Classifier: Natural Language :: English
Classifier: Operating System :: OS Independent
Classifier: Programming Language :: Python :: 2
Classifier: Topic :: Internet
Classifier: Topic :: Internet :: WWW/HTTP
